T_flipflop.v
module tflipflop(clk,rst,prt,ld,a,t,Q,QB);
input clk,rst,prt,t,ld,a;
output reg Q,QB;
always @ (posedge clk) begin
        if(rst) begin
                Q<=0;
                QB<=1;
        end else if(prt) begin
                Q<=1;
                QB<=0;
        end else if(ld) begin
                Q<=a;
                QB<=~a;
        end else begin
                if(t) begin
                        Q<=~Q;
                        QB<=~QB;
                end else begin
                        Q<=Q;
                        QB<=QB;
                end
        end
end
endmodule

updowncounter.v
`timescale 1ns / 1ps
module updowncounter_tb;
reg clk,rst,prt,ld;
reg [2:0] a;
wire [2:0]Q,QB;
reg ud;
tflipflop t0(clk,rst,prt,ld,a[0],1'b1,Q[0],QB[0]);
tflipflop t1(clk,rst,prt,ld,a[1],ud ^ Q[0],Q[1],QB[1]);
tflipflop t2(clk,rst,prt,ld,a[2],(~ud & Q[0] & Q[1]) | (ud & QB[0] & QB[1]),Q[2],QB[2]);
initial begin
clk=0;
end
always #5 clk=~clk;
initial begin
$dumpfile("dump.vcd");
$dumpvars(0, updowncounter_tb);
$monitor("at time %t: clk=%b rst=%b prt=%b ld=%b a=%d ud=%b Q=%d",$time,clk,rst,prt,ld,a,ud,Q);
                rst = 1; ud = 0; ld = 0; prt = 0;#10;
                rst = 0; ud = 0; ld = 0; prt = 0;#90;
                prt = 1; ud = 0; ld = 0; #10;
                prt = 0; ud = 0; ld = 0; #90;
                rst = 1; ud = 1; ld = 0; #10;
                rst = 0; ud = 1; ld = 0; #90;
                prt = 1; ud = 1; ld = 0; #10;
                prt = 0; ud = 1; ld = 0; #90;
                ud = 0; ld = 1; a = 3'b101; #11; 
                ld = 0; #89;
                ud = 1; ld = 1; a = 3'b100; #11;
                ld = 0; #89;
                ud = 0; #100;
        $finish;
end
endmodule

dump.vcd
$date
	Sun Jul 19 18:48:23 2026
$end
$version
	Icarus Verilog
$end
$timescale
	1ps
$end
$scope module updowncounter_tb $end
$var wire 3 ! QB [2:0] $end
$var wire 3 " Q [2:0] $end
$var reg 3 # a [2:0] $end
$var reg 1 $ clk $end
$var reg 1 % ld $end
$var reg 1 & prt $end
$var reg 1 ' rst $end
$var reg 1 ( ud $end
$scope module t0 $end
$var wire 1 ) a $end
$var wire 1 $ clk $end
$var wire 1 % ld $end
$var wire 1 & prt $end
$var wire 1 ' rst $end
$var wire 1 * t $end
$var reg 1 + Q $end
$var reg 1 , QB $end
$upscope $end
$scope module t1 $end
$var wire 1 - a $end
$var wire 1 $ clk $end
$var wire 1 % ld $end
$var wire 1 & prt $end
$var wire 1 ' rst $end
$var wire 1 . t $end
$var reg 1 / Q $end
$var reg 1 0 QB $end
$upscope $end
$scope module t2 $end
$var wire 1 1 a $end
$var wire 1 $ clk $end
$var wire 1 % ld $end
$var wire 1 & prt $end
$var wire 1 ' rst $end
$var wire 1 2 t $end
$var reg 1 3 Q $end
$var reg 1 4 QB $end
$upscope $end
$upscope $end
$enddefinitions $end
$comment Show the parameter values. $end
$dumpall
$end
#0
$dumpvars
x4
x3
x2
x1
x0
x/
x.
x-
x,
x+
1*
x)
0(
1'
0&
0%
0$
bx #
bx "
bx !
$end
#5000
02
0.
1,
0+
10
0/
b111 !
14
b0 "
03
1$
#10000
0$
0'
#15000
1.
b110 !
0,
b1 "
1+
1$
#20000
0$
#25000
02
0.
1,
0+
b101 !
00
b10 "
1/
1$
#30000
0$
#35000
12
1.
b100 !
0,
b11 "
1+
1$
#40000
0$
#45000
02
0.
1,
0+
10
0/
b11 !
04
b100 "
13
1$
#50000
0$
#55000
1.
b10 !
0,
b101 "
1+
1$
#60000
0$
#65000
02
0.
1,
0+
b1 !
00
b110 "
1/
1$
#70000
0$
#75000
12
1.
b0 !
0,
b111 "
1+
1$
#80000
0$
#85000
02
0.
1,
0+
10
0/
b111 !
14
b0 "
03
1$
#90000
0$
#95000
1.
b110 !
0,
b1 "
1+
1$
#100000
0$
1&
#105000
12
00
1/
b0 !
04
b111 "
13
1$
#110000
0$
0&
#115000
02
0.
14
03
10
0/
b111 !
1,
b0 "
0+
1$
#120000
0$
#125000
1.
b110 !
0,
b1 "
1+
1$
#130000
0$
#135000
0.
00
1/
b101 !
1,
b10 "
0+
1$
#140000
0$
#145000
12
1.
b100 !
0,
b11 "
1+
1$
#150000
0$
#155000
02
0.
04
13
10
0/
b11 !
1,
b100 "
0+
1$
#160000
0$
#165000
1.
b10 !
0,
b101 "
1+
1$
#170000
0$
#175000
0.
00
1/
b1 !
1,
b110 "
0+
1$
#180000
0$
#185000
12
1.
b0 !
0,
b111 "
1+
1$
#190000
0$
#195000
02
0.
14
03
10
0/
b111 !
1,
b0 "
0+
1$
#200000
12
1.
0$
1(
1'
#205000
1$
#210000
0$
0'
#215000
02
0.
04
13
00
1/
b0 !
0,
b111 "
1+
1$
#220000
0$
#225000
1.
b1 !
1,
b110 "
0+
1$
#230000
0$
#235000
0.
10
0/
b10 !
0,
b101 "
1+
1$
#240000
0$
#245000
12
1.
b11 !
1,
b100 "
0+
1$
#250000
0$
#255000
02
0.
14
03
00
1/
b100 !
0,
b11 "
1+
1$
#260000
0$
#265000
1.
b101 !
1,
b10 "
0+
1$
#270000
0$
#275000
0.
10
0/
b110 !
0,
b1 "
1+
1$
#280000
0$
#285000
12
1.
b111 !
1,
b0 "
0+
1$
#290000
0$
#295000
02
0.
04
13
00
1/
b0 !
0,
b111 "
1+
1$
#300000
0$
1&
#305000
1$
#310000
0$
0&
#315000
1.
b1 !
1,
b110 "
0+
1$
#320000
0$
#325000
02
0.
0,
1+
b10 !
10
b101 "
0/
1$
#330000
0$
#335000
12
1.
b11 !
1,
b100 "
0+
1$
#340000
0$
#345000
02
0.
0,
1+
00
1/
b100 !
14
b11 "
03
1$
#350000
0$
#355000
1.
b101 !
1,
b10 "
0+
1$
#360000
0$
#365000
02
0.
0,
1+
b110 !
10
b1 "
0/
1$
#370000
0$
#375000
12
1.
b111 !
1,
b0 "
0+
1$
#380000
0$
#385000
02
0.
0,
1+
00
1/
b0 !
04
b111 "
13
1$
#390000
0$
#395000
1.
b1 !
1,
b110 "
0+
1$
#400000
1)
0-
11
0.
0$
b101 #
1%
0(
#405000
1.
0,
1+
b10 !
10
b101 "
0/
1$
#410000
0$
#411000
0%
#415000
0.
00
1/
b1 !
1,
b110 "
0+
1$
#420000
0$
#425000
12
1.
b0 !
0,
b111 "
1+
1$
#430000
0$
#435000
02
0.
14
03
10
0/
b111 !
1,
b0 "
0+
1$
#440000
0$
#445000
1.
b110 !
0,
b1 "
1+
1$
#450000
0$
#455000
0.
00
1/
b101 !
1,
b10 "
0+
1$
#460000
0$
#465000
12
1.
b100 !
0,
b11 "
1+
1$
#470000
0$
#475000
02
0.
04
13
10
0/
b11 !
1,
b100 "
0+
1$
#480000
0$
#485000
1.
b10 !
0,
b101 "
1+
1$
#490000
0$
#495000
0.
00
1/
b1 !
1,
b110 "
0+
1$
#500000
0)
1.
0$
b100 #
1%
1(
#505000
12
b11 !
10
b100 "
0/
1$
#510000
0$
#511000
0%
#515000
02
0.
14
03
00
1/
b100 !
0,
b11 "
1+
1$
#520000
0$
#525000
1.
b101 !
1,
b10 "
0+
1$
#530000
0$
#535000
0.
10
0/
b110 !
0,
b1 "
1+
1$
#540000
0$
#545000
12
1.
b111 !
1,
b0 "
0+
1$
#550000
0$
#555000
02
0.
04
13
00
1/
b0 !
0,
b111 "
1+
1$
#560000
0$
#565000
1.
b1 !
1,
b110 "
0+
1$
#570000
0$
#575000
0.
10
0/
b10 !
0,
b101 "
1+
1$
#580000
0$
#585000
12
1.
b11 !
1,
b100 "
0+
1$
#590000
0$
#595000
02
0.
14
03
00
1/
b100 !
0,
b11 "
1+
1$
#600000
12
1.
0$
0(
#605000
02
0.
1,
0+
10
0/
b11 !
04
b100 "
13
1$
#610000
0$
#615000
1.
b10 !
0,
b101 "
1+
1$
#620000
0$
#625000
02
0.
1,
0+
b1 !
00
b110 "
1/
1$
#630000
0$
#635000
12
1.
b0 !
0,
b111 "
1+
1$
#640000
0$
#645000
02
0.
1,
0+
10
0/
b111 !
14
b0 "
03
1$
#650000
0$
#655000
1.
b110 !
0,
b1 "
1+
1$
#660000
0$
#665000
02
0.
1,
0+
b101 !
00
b10 "
1/
1$
#670000
0$
#675000
12
1.
b100 !
0,
b11 "
1+
1$
#680000
0$
#685000
02
0.
1,
0+
10
0/
b11 !
04
b100 "
13
1$
#690000
0$
#695000
1.
b10 !
0,
b101 "
1+
1$
